{
  "name": "Lily Saunders",
  "age": 37,
  "address": {
    "street": "Dimden Boulevard",
    "city": "Gucdiicu",
    "state": "AL",
    "zip": "56063"
  },
  "contact": {
    "phone": "(907) 417-6275",
    "servicePhone": "800125892"
  },
  "birthday": "1980-09-29T01:09:10.178Z",
  "ip": "41.145.57.182",
  "foo": "bar",
  "profile": {
    "about": "Butfu kacigvov lup emnefon ohiopiji gezoh ikwuw lakeis jofajnak ka ecman loviz pev luzeti. Cuhlab pow avgu sizcarnu igve hi opajec tuzbekbo wol ipa lije wim boovu. Gavdoj rofejda epove vez sohpe samonav dula on tuvborsaf evo ce suniri emce weksaf dezit ogeejaopu wafrow kupepsan. Wijiha dineblo jatvetuc mu jettu fib padva huj mu lupvif ubahe sildow cuufraw vi wo. Guraza silrecu co daje pek gufuvowaw huibka itopahev fefza fukawhum av ruk uz nolnide rop pocosmov luefuso etian.",
    "bio": "Cufzog oj hesajo virev ka za uni iroza rurfe cific udo fe haketowe vajodpes kofuwi zis feb. Do ta gines juot dijutofa nonnuji mebagci tiako guhu mokcig me suvbo wafi uk ik. Tubu su pohovit doc si ishow fi jaafuko ruffies widar jolivmu ni cugrihze refovat we so ciku tej. Na mito duufu wijef wumalfip nitepam soiki is mojijwu osu logbaade voki op. Bafpu saopu lo jefmi morfaka ragamdah wu akwiacu ablot hitihudo kehojwo wigwuji ocauve om fable fa. Zemadwo fenin fuj luuwe dioccak ipu gozjud katiszo voer ita ge emoic."
  },
  "apiKey": "da85dc1ef6ac50fd64e3e108eff58728cfca71d3dc9c50515cf242fc93d7eca3",
  "currency": {
    "code": "LAK",
    "name": "Laos Kip"
  }
}