{
  "name": "Seth Quinn",
  "age": 47,
  "address": {
    "street": "Muohi Drive",
    "city": "Neegeje",
    "state": "NV",
    "zip": "35570"
  },
  "contact": {
    "phone": "(784) 791-8023",
    "servicePhone": "800269686"
  },
  "birthday": "2001-06-17T06:00:59.525Z",
  "ip": "16.70.98.186",
  "foo": "bar",
  "profile": {
    "about": "Vieruvu juublol laho vube fiona zidrikup kagpetom okbap jigcumod mulvimtu ol gebeviho hunonu efofulzel lirdautu ok tawacok. Posal oljek koczad ikpati fohim vu va ros kul wez sec wefnabi mejaasa bagbe sudwobeg uc ki gapiig. Akmiup suuje zaj guj ifu ikuwur ez igonek ju kiwapuv egsupu kuz ehzurus ah. Uj se nusih saccin ursu tomhendij teziz muwbozvup dok sohurkuh losti gughe umepefup.",
    "bio": "Dofipa kewdip gujenu ripapob dudel git wucripzob vihseb teruw sufwek ovo it fi vevdotre daesu. Vukap lenlu cappikhis huvo teswudroj noz mahnuhlu pirsa rezhi luw du azuduk hak ikoul hucaruw. Eme rawoaf utbu puv tuozadu zabow zihciwfoc valtitu umudance teghovba em rokaiwu."
  },
  "apiKey": "f0e3d71d70ccbbcd078bebb5a437a59898fc06588836147481ae3e410747f195",
  "currency": {
    "code": "TND",
    "name": "Tunisia Dinar"
  }
}